abgeordnetenwatch_python/__init__.py
abgeordnetenwatch_python/cache.py
abgeordnetenwatch_python/cli/__init__.py
abgeordnetenwatch_python/cli/convert_qa.py
abgeordnetenwatch_python/cli/load_parliament_qa.py
abgeordnetenwatch_python/cli/load_questions_answers.py
abgeordnetenwatch_python/models/__init__.py
abgeordnetenwatch_python/models/candidacy_mandate.py
abgeordnetenwatch_python/models/parliament.py
abgeordnetenwatch_python/models/parliament_period.py
abgeordnetenwatch_python/models/party.py
abgeordnetenwatch_python/models/politician_dossier.py
abgeordnetenwatch_python/models/politicians.py
abgeordnetenwatch_python/models/questions_answers.py
abgeordnetenwatch_python/questions_answers/__init__.py
abgeordnetenwatch_python/questions_answers/load_qa.py
abgeordnetenwatch_python-0.1.0.dist-info/licenses/LICENSE
test_scripts/test.py
abgeordnetenwatch_python-0.1.0.dist-info/METADATA
abgeordnetenwatch_python-0.1.0.dist-info/WHEEL
abgeordnetenwatch_python-0.1.0.dist-info/entry_points.txt
abgeordnetenwatch_python-0.1.0.dist-info/top_level.txt
abgeordnetenwatch_python-0.1.0.dist-info/RECORD
