Metadata-Version: 2.4
Name: abgeordnetenwatch_python
Version: 0.1.0
Summary: Fetch questions and answers from german politicians via python classes.
Author-email: Bruno Schilling <bruno.schilling@protonmail.ch>
License: GPL-3.0-only
Requires-Python: >=3.11
License-File: LICENSE
Requires-Dist: beautifulsoup4>=4.12
Requires-Dist: tqdm>=4.66
Requires-Dist: aiohttp>=3.11
Requires-Dist: pydantic>=2.11
Provides-Extra: dev
Requires-Dist: pytest; extra == "dev"
Dynamic: license-file
